[
  {
    "id": 1,
    "name": "ರೊಮ್ಯಾಂಟಿಕ್ ಗಾರ್ಡನ್",
    "category": "ಮದುವೆ",
    "imageUrl": "https://images.unsplash.com/photo-1606800052052-a08af7148866?w=400&h=300&fit=crop",
    "isPopular": true
  },
  {
    "id": 2,
    "name": "ಆಧುನಿಕ ಮಿನಿಮಲಿಸ್ಟ್",
    "category": "ಮದುವೆ",
    "imageUrl": "https://images.unsplash.com/photo-1591604466107-ec97de577aff?w=400&h=300&fit=crop",
    "isPopular": false
  },
  {
    "id": 3,
    "name": "ವಿಂಟೇಜ್ ಸೆಲೆಬ್ರೇಶನ್",
    "category": "ಹುಟ್ಟುಹಬ್ಬ",
    "imageUrl": "https://images.unsplash.com/photo-1464347744102-11db6282f854?w=400&h=300&fit=crop",
    "isPopular": true
  },
  {
    "id": 4,
    "name": "ಎಕ್ಸಿಕ್ಯೂಟಿವ್ ಸಮ್ಮಿಟ್",
    "category": "ಕಾರ್ಪೊರೇಟ್",
    "imageUrl": "https://images.unsplash.com/photo-1540575467063-178a50c2df87?w=400&h=300&fit=crop",
    "isPopular": false
  },
  {
    "id": 5,
    "name": "ಸ್ವೀಟ್ ಡ್ರೀಮ್ಸ್",
    "category": "ಬೇಬಿ ಶವರ್",
    "imageUrl": "https://images.unsplash.com/photo-1515488042361-ee00e0ddd4e4?w=400&h=300&fit=crop",
    "isPopular": true
  },
  {
    "id": 6,
    "name": "ಹಾಯಿಗೆ ಸ್ವಾಗತ",
    "category": "ಗೃಹಪ್ರವೇಶ",
    "imageUrl": "https://images.unsplash.com/photo-1600585154340-be6161a56a0c?w=400&h=300&fit=crop",
    "isPopular": false
  }
]
